{
  "name": "hotel-connector",
  "config": {
    "connector.class": "io.debezium.connector.postgresql.PostgresConnector",
    "plugin.name": "pgoutput",
    "database.hostname": "${DB_HOST}",
    "database.user": "${DBZ_USER}",
    "database.password": "${DBZ_PASSWORD}",
    "database.dbname": "${DB_NAME}",
    "topic.prefix": "${DB_NAME}",
    "schema.include.list": "public",
    "snapshot.mode": "when_needed",
		"tasks.max": "1",
		"database.port": "5432",
		"database.server.id": "1",
		"database.include.list": "${DB_NAME}",
		"schema.history.internal.kafka.topic": "${DB_NAME}-schema",
		"schema.history.internal.kafka.bootstrap.servers": "${KAFKA_BOOTSTRAP_SERVER}",
		"schema.history.internal.consumer.security.protocol": "SASL_SSL",
		"schema.history.internal.consumer.sasl.mechanism": "AWS_MSK_IAM",
		"schema.history.internal.consumer.sasl.jaas.config": "software.amazon.msk.auth.iam.IAMLoginModule required;",
		"schema.history.internal.consumer.sasl.client.callback.handler.class": "software.amazon.msk.auth.iam.IAMClientCallbackHandler",
		"schema.history.internal.producer.security.protocol": "SASL_SSL",
		"schema.history.internal.producer.sasl.mechanism": "AWS_MSK_IAM",
		"schema.history.internal.producer.sasl.jaas.config": "software.amazon.msk.auth.iam.IAMLoginModule required;",
		"schema.history.internal.producer.sasl.client.callback.handler.class": "software.amazon.msk.auth.iam.IAMClientCallbackHandler",
		"include.schema.changes": "true"
  }
}
